pyproject2setuppy/__init__.py
pyproject2setuppy/__init__.pyc
pyproject2setuppy/__main__.py
pyproject2setuppy/__main__.pyc
pyproject2setuppy/common.py
pyproject2setuppy/common.pyc
pyproject2setuppy/flit.py
pyproject2setuppy/flit.pyc
pyproject2setuppy/main.py
pyproject2setuppy/main.pyc
pyproject2setuppy/pep621.py
pyproject2setuppy/pep621.pyc
pyproject2setuppy/poetry.py
pyproject2setuppy/poetry.pyc
pyproject2setuppy/setuptools.py
pyproject2setuppy/setuptools.pyc
pyproject2setuppy-22.dist-info/COPYING
pyproject2setuppy-22.dist-info/METADATA
pyproject2setuppy-22.dist-info/WHEEL
pyproject2setuppy-22.dist-info/top_level.txt
pyproject2setuppy-22.dist-info/RECORD
